{"modules":{"ti.barcode.BarcodeModule":{"apiName":"Barcode"}},"proxies":{"ti.barcode.BarcodeModule":{"proxyClassName":"BarcodeModule","methods":{"getUseLED":{"hasInvocation":false,"defaultValueProvider":"org.appcelerator.kroll.KrollConverter","apiName":"getUseLED","runOnUiThread":false,"converter":"org.appcelerator.kroll.KrollConverter","args":[],"name":"__default_name__","returnType":"boolean"},"getHasLED":{"hasInvocation":false,"defaultValueProvider":"org.appcelerator.kroll.KrollConverter","apiName":"getHasLED","runOnUiThread":false,"converter":"org.appcelerator.kroll.KrollConverter","args":[],"name":"__default_name__","returnType":"boolean"},"setUseFrontCamera":{"hasInvocation":false,"defaultValueProvider":"org.appcelerator.kroll.KrollConverter","apiName":"setUseFrontCamera","runOnUiThread":false,"converter":"org.appcelerator.kroll.KrollConverter","args":[{"defaultValueProvider":"org.appcelerator.kroll.KrollConverter","converter":"org.appcelerator.kroll.KrollConverter","sourceName":"value","name":"value","type":"boolean"}],"name":"__default_name__","returnType":"void"},"setUseLED":{"hasInvocation":false,"defaultValueProvider":"org.appcelerator.kroll.KrollConverter","apiName":"setUseLED","runOnUiThread":false,"converter":"org.appcelerator.kroll.KrollConverter","args":[{"defaultValueProvider":"org.appcelerator.kroll.KrollConverter","converter":"org.appcelerator.kroll.KrollConverter","sourceName":"value","name":"value","type":"boolean"}],"name":"__default_name__","returnType":"void"},"capture":{"hasInvocation":false,"defaultValueProvider":"org.appcelerator.kroll.KrollConverter","apiName":"capture","runOnUiThread":false,"converter":"org.appcelerator.kroll.KrollConverter","args":[{"defaultValueProvider":"org.appcelerator.kroll.KrollConverter","converter":"org.appcelerator.kroll.KrollConverter","sourceName":"args","name":"args","optional":true,"type":"java.util.HashMap"}],"name":"__default_name__","returnType":"void"},"getHasCamera":{"hasInvocation":false,"defaultValueProvider":"org.appcelerator.kroll.KrollConverter","apiName":"getHasCamera","runOnUiThread":false,"converter":"org.appcelerator.kroll.KrollConverter","args":[],"name":"__default_name__","returnType":"boolean"},"cancel":{"hasInvocation":false,"defaultValueProvider":"org.appcelerator.kroll.KrollConverter","apiName":"cancel","runOnUiThread":false,"converter":"org.appcelerator.kroll.KrollConverter","args":[],"name":"__default_name__","returnType":"void"},"getUseFrontCamera":{"hasInvocation":false,"defaultValueProvider":"org.appcelerator.kroll.KrollConverter","apiName":"getUseFrontCamera","runOnUiThread":false,"converter":"org.appcelerator.kroll.KrollConverter","args":[],"name":"__default_name__","returnType":"boolean"},"parse":{"hasInvocation":false,"defaultValueProvider":"org.appcelerator.kroll.KrollConverter","apiName":"parse","runOnUiThread":false,"converter":"org.appcelerator.kroll.KrollConverter","args":[{"defaultValueProvider":"org.appcelerator.kroll.KrollConverter","converter":"org.appcelerator.kroll.KrollConverter","sourceName":"args","name":"args","optional":false,"type":"java.util.HashMap"}],"name":"__default_name__","returnType":"void"}},"superProxyClassName":"KrollModule","superProxyBindingClassName":"org.appcelerator.kroll.KrollModuleBindingGen","proxyAttrs":{"proxyClassName":"ti.barcode.BarcodeModule","id":"ti.barcode","propertyAccessors":["displayedMessage","allowRotation","allowMenu","allowInstructions"],"isTopLevel":false,"name":"Barcode","fullAPIName":"Barcode"},"packageName":"ti.barcode","dynamicProperties":{"useFrontCamera":{"setDefaultProviders":["org.appcelerator.kroll.KrollConverter"],"getMethodArgs":[],"get":true,"runOnUiThread":false,"set":true,"getHasInvocation":false,"getMethodName":"getUseFrontCamera","getReturnType":"boolean","setMethodArgs":[{"defaultValueProvider":"org.appcelerator.kroll.KrollConverter","converter":"org.appcelerator.kroll.KrollConverter","sourceName":"value","name":"value","type":"boolean"}],"setReturnType":"void","javascriptConverter":"org.appcelerator.kroll.KrollConverter","getDefaultProviders":[],"defaultValueProvider":"org.appcelerator.kroll.KrollConverter","converter":"org.appcelerator.kroll.KrollConverter","name":"useFrontCamera","retain":true,"setMethodName":"setUseFrontCamera","nativeConverter":"org.appcelerator.kroll.KrollConverter","setHasInvocation":false},"hasCamera":{"getMethodArgs":[],"get":true,"runOnUiThread":false,"set":false,"getHasInvocation":false,"getMethodName":"getHasCamera","getReturnType":"boolean","javascriptConverter":"org.appcelerator.kroll.KrollConverter","getDefaultProviders":[],"defaultValueProvider":"org.appcelerator.kroll.KrollConverter","converter":"org.appcelerator.kroll.KrollConverter","name":"hasCamera","nativeConverter":"org.appcelerator.kroll.KrollConverter","setHasInvocation":false},"useLED":{"setDefaultProviders":["org.appcelerator.kroll.KrollConverter"],"getMethodArgs":[],"get":true,"runOnUiThread":false,"set":true,"getHasInvocation":false,"getMethodName":"getUseLED","getReturnType":"boolean","setMethodArgs":[{"defaultValueProvider":"org.appcelerator.kroll.KrollConverter","converter":"org.appcelerator.kroll.KrollConverter","sourceName":"value","name":"value","type":"boolean"}],"setReturnType":"void","javascriptConverter":"org.appcelerator.kroll.KrollConverter","getDefaultProviders":[],"defaultValueProvider":"org.appcelerator.kroll.KrollConverter","converter":"org.appcelerator.kroll.KrollConverter","name":"useLED","retain":true,"setMethodName":"setUseLED","nativeConverter":"org.appcelerator.kroll.KrollConverter","setHasInvocation":false},"hasLED":{"getMethodArgs":[],"get":true,"runOnUiThread":false,"set":false,"getHasInvocation":false,"getMethodName":"getHasLED","getReturnType":"boolean","javascriptConverter":"org.appcelerator.kroll.KrollConverter","getDefaultProviders":[],"defaultValueProvider":"org.appcelerator.kroll.KrollConverter","converter":"org.appcelerator.kroll.KrollConverter","name":"hasLED","nativeConverter":"org.appcelerator.kroll.KrollConverter","setHasInvocation":false}},"sourceName":"ti.barcode.BarcodeModuleBindingGen","superPackageName":"org.appcelerator.kroll","isModule":true,"genClassName":"BarcodeModuleBindingGen","constants":{"FORMAT_UPC_A":{"name":"FORMAT_UPC_A","value":4,"proxyName":"FORMAT_UPC_A","type":"int"},"GEOLOCATION":{"name":"GEOLOCATION","value":6,"proxyName":"GEOLOCATION","type":"int"},"FORMAT_UPC_E":{"name":"FORMAT_UPC_E","value":3,"proxyName":"FORMAT_UPC_E","type":"int"},"UNKNOWN":{"name":"UNKNOWN","value":0,"proxyName":"UNKNOWN","type":"int"},"TELEPHONE":{"name":"TELEPHONE","value":3,"proxyName":"TELEPHONE","type":"int"},"FORMAT_QR_CODE":{"name":"FORMAT_QR_CODE","value":1,"proxyName":"FORMAT_QR_CODE","type":"int"},"FORMAT_CODE_39":{"name":"FORMAT_CODE_39","value":8,"proxyName":"FORMAT_CODE_39","type":"int"},"CONTACT":{"name":"CONTACT","value":8,"proxyName":"CONTACT","type":"int"},"BOOKMARK":{"name":"BOOKMARK","value":9,"proxyName":"BOOKMARK","type":"int"},"FORMAT_ITF":{"name":"FORMAT_ITF","value":9,"proxyName":"FORMAT_ITF","type":"int"},"WIFI":{"name":"WIFI","value":10,"proxyName":"WIFI","type":"int"},"FORMAT_CODE_128":{"name":"FORMAT_CODE_128","value":7,"proxyName":"FORMAT_CODE_128","type":"int"},"CALENDAR":{"name":"CALENDAR","value":5,"proxyName":"CALENDAR","type":"int"},"FORMAT_EAN_8":{"name":"FORMAT_EAN_8","value":5,"proxyName":"FORMAT_EAN_8","type":"int"},"FORMAT_NONE":{"name":"FORMAT_NONE","value":0,"proxyName":"FORMAT_NONE","type":"int"},"TEXT":{"name":"TEXT","value":4,"proxyName":"TEXT","type":"int"},"FORMAT_EAN_13":{"name":"FORMAT_EAN_13","value":6,"proxyName":"FORMAT_EAN_13","type":"int"},"FORMAT_DATA_MATRIX":{"name":"FORMAT_DATA_MATRIX","value":2,"proxyName":"FORMAT_DATA_MATRIX","type":"int"},"EMAIL":{"name":"EMAIL","value":7,"proxyName":"EMAIL","type":"int"},"URL":{"name":"URL","value":1,"proxyName":"URL","type":"int"},"SMS":{"name":"SMS","value":2,"proxyName":"SMS","type":"int"}}}}}